gSheetsTask/__init__.py
gSheetsTask/code.py
gSheetsTask-0.2.dist-info/LICENSE.txt
gSheetsTask-0.2.dist-info/METADATA
gSheetsTask-0.2.dist-info/WHEEL
gSheetsTask-0.2.dist-info/top_level.txt
gSheetsTask-0.2.dist-info/RECORD
